setup.cfg
setup.py
bootycall/__init__.py
bootycall/bcall.py
bootycall.egg-info/PKG-INFO
bootycall.egg-info/SOURCES.txt
bootycall.egg-info/dependency_links.txt
bootycall.egg-info/entry_points.txt
bootycall.egg-info/requires.txt
bootycall.egg-info/top_level.txt