Metadata-Version: 1.0
Name: bootycall
Version: 0.1.1
Summary: A shell nREPL client for boot nREPL and other nREPls.
Home-page: https://github.com/christo-auer/bootycall
Author: Christopher Auer
Author-email: high.on.bonsai@googlemail.com
License: UNKNOWN
Keywords: nrepl,clojure,boot,leiningen
Platform: UNKNOWN
